examples/basecall_gpudecode.py
examples/__init__.py
koi/build.py
koi/ctc.py
koi/decode.py
koi/lstm.py
koi/utils.py
koi/_runtime.pyd
koi/__init__.py
koi/3rdparty/cutlass/examples/40_cutlass_py/conv2d.py
koi/3rdparty/cutlass/examples/40_cutlass_py/gemm.py
koi/3rdparty/cutlass/examples/40_cutlass_py/gemm_grouped.py
koi/3rdparty/cutlass/examples/40_cutlass_py/customizable/conv2d.py
koi/3rdparty/cutlass/examples/40_cutlass_py/customizable/gemm.py
koi/3rdparty/cutlass/examples/40_cutlass_py/customizable/gemm_grouped.py
koi/3rdparty/cutlass/examples/41_fused_multi_head_attention/fmha_backward_test.py
koi/3rdparty/cutlass/examples/41_fused_multi_head_attention/piped_subprocess.py
koi/3rdparty/cutlass/examples/44_multi_gemm_ir_and_codegen/ir_gen/gen_all_code.py
koi/3rdparty/cutlass/examples/44_multi_gemm_ir_and_codegen/ir_gen/gen_cmake.py
koi/3rdparty/cutlass/examples/44_multi_gemm_ir_and_codegen/ir_gen/gen_customized_epilogue.py
koi/3rdparty/cutlass/examples/44_multi_gemm_ir_and_codegen/ir_gen/gen_device.py
koi/3rdparty/cutlass/examples/44_multi_gemm_ir_and_codegen/ir_gen/gen_ir.py
koi/3rdparty/cutlass/examples/44_multi_gemm_ir_and_codegen/ir_gen/gen_kernel.py
koi/3rdparty/cutlass/examples/44_multi_gemm_ir_and_codegen/ir_gen/gen_sample.py
koi/3rdparty/cutlass/examples/44_multi_gemm_ir_and_codegen/ir_gen/gen_threadblock.py
koi/3rdparty/cutlass/examples/44_multi_gemm_ir_and_codegen/ir_gen/gen_turing_and_volta.py
koi/3rdparty/cutlass/examples/44_multi_gemm_ir_and_codegen/ir_gen/gen_verify.py
koi/3rdparty/cutlass/examples/44_multi_gemm_ir_and_codegen/ir_gen/helper.py
koi/3rdparty/cutlass/examples/44_multi_gemm_ir_and_codegen/ir_gen/replace_fix_impl_header.py
koi/3rdparty/cutlass/python/setup.py
koi/3rdparty/cutlass/python/cutlass/epilogue.py
koi/3rdparty/cutlass/python/cutlass/library_defaults.py
koi/3rdparty/cutlass/python/cutlass/swizzle.py
koi/3rdparty/cutlass/python/cutlass/__init__.py
koi/3rdparty/cutlass/python/cutlass/backend/arguments.py
ont_koi-0.6.2.dist-info/DELVEWHEEL
ont_koi-0.6.2.dist-info/METADATA
ont_koi-0.6.2.dist-info/RECORD
ont_koi-0.6.2.dist-info/top_level.txt
ont_koi-0.6.2.dist-info/WHEEL
ont_koi-0.6.2.dist-info/licenses/LICENCE.md
