Metadata-Version: 2.4
Name: ont-koi
Version: 0.6.2
Requires-Python: >=3.9
License-File: LICENCE.md
Requires-Dist: cffi
Provides-Extra: test
Requires-Dist: numpy; extra == "test"
Requires-Dist: pytest; extra == "test"
Dynamic: license-file
